{
    "PFA029M": [
        1,
        "上層"
    ],
    "PFA054M": [
        1,
        "上層"
    ],
    "PFA090M": [
        1,
        "上層"
    ],
    "PGA060M": [
        1,
        "上層"
    ],
    "PGA034M": [
        1,
        "上層"
    ],
    "PGA097M": [
        1,
        "上層"
    ],
    "PGA108M": [
        1,
        "上層"
    ],
    "PGA109M": [
        1,
        "上層"
    ],
    "PGB014M": [
        1,
        "上層"
    ],
    "PGB022M": [
        1,
        "上層"
    ],
    "PGB030M": [
        1,
        "上層"
    ],
    "PGB050M": [
        1,
        "上層"
    ],
    "PGB056M": [
        1,
        "上層"
    ],
    "PGB058M": [
        1,
        "上層"
    ],
    "PGC002M": [
        1,
        "上層"
    ],
    "PFC042M": [
        1,
        "下層"
    ],
    "PFC066M": [
        1,
        "下層"
    ],
    "PFC067M": [
        1,
        "下層"
    ],
    "PGA050M": [
        1,
        "下層"
    ],
    "PGA048M": [
        1,
        "下層"
    ],
    "PGA054M": [
        1,
        "下層"
    ],
    "PGC020M": [
        1,
        "下層"
    ],
    "PGC037M": [
        1,
        "下層"
    ],
    "PGC051M": [
        1,
        "下層"
    ],
    "PGF050M": [
        1,
        "下層"
    ],
    "PGF066M": [
        1,
        "下層"
    ],
    "PGF070M": [
        1,
        "下層"
    ],
    "PGF001M": [
        5,
        "第二層"
    ],
    "PGG008M": [
        1,
        "下層"
    ],
    "PGG077M": [
        1,
        "下層"
    ],
    "PGG098M": [
        1,
        "下層"
    ],
    "上層": [
        8,
        "最上層"
    ],
    "PFA100M": [
        2,
        "上層"
    ],
    "PFA101M": [
        2,
        "上層"
    ],
    "PFA119M": [
        2,
        "上層"
    ],
    "PFA125M": [
        2,
        "上層"
    ],
    "PFA124M": [
        7,
        "最下層"
    ],
    "PFA139M": [
        2,
        "上層"
    ],
    "PFA137M": [
        2,
        "上層"
    ],
    "PFA136M": [
        7,
        "最下層"
    ],
    "PFA140M": [
        2,
        "上層"
    ],
    "PFA142M": [
        2,
        "上層"
    ],
    "PFA144M": [
        2,
        "上層"
    ],
    "PFA145M": [
        2,
        "上層"
    ],
    "PFC010M": [
        2,
        "上層"
    ],
    "PFC007M": [
        2,
        "上層"
    ],
    "PFC069M": [
        2,
        "下層"
    ],
    "PFC072M": [
        2,
        "下層"
    ],
    "PFC084M": [
        2,
        "下層"
    ],
    "PFC081M": [
        2,
        "下層"
    ],
    "PFC073M": [
        2,
        "下層"
    ],
    "PFD025M": [
        2,
        "下層"
    ],
    "PFE034M": [
        2,
        "下層"
    ],
    "PFE052M": [
        2,
        "下層"
    ],
    "PFE053M": [
        2,
        "下層"
    ],
    "PGA001M": [
        2,
        "下層"
    ],
    "PGA003M": [
        2,
        "下層"
    ],
    "PGA006M": [
        2,
        "下層"
    ],
    "PGA030M": [
        2,
        "下層"
    ],
    "PBA036M": [
        3,
        "上層"
    ],
    "PBA052M": [
        3,
        "上層"
    ],
    "PBA061M": [
        3,
        "上層"
    ],
    "PBA065M": [
        3,
        "上層"
    ],
    "PCB013M": [
        3,
        "上層"
    ],
    "PCC210M": [
        3,
        "上層"
    ],
    "PCC324M": [
        3,
        "上層"
    ],
    "PAA051M": [
        3,
        "上層"
    ],
    "PCF004M": [
        3,
        "上層"
    ],
    "PCF032M": [
        3,
        "上層"
    ],
    "PCF036M": [
        3,
        "上層"
    ],
    "PCH005M": [
        3,
        "上層"
    ],
    "PCH078M": [
        3,
        "上層"
    ],
    "PCH132M": [
        3,
        "上層"
    ],
    "PDA101M": [
        3,
        "下層"
    ],
    "PCG042M": [
        3,
        "下層"
    ],
    "PDA146M": [
        3,
        "下層"
    ],
    "PDA102M": [
        3,
        "下層"
    ],
    "PEB003M": [
        3,
        "下層"
    ],
    "PEB014M": [
        3,
        "下層"
    ],
    "PEC002M": [
        3,
        "下層"
    ],
    "PEC004M": [
        3,
        "下層"
    ],
    "PED044M": [
        3,
        "下層"
    ],
    "PED069M": [
        3,
        "下層"
    ],
    "PED070M": [
        3,
        "下層"
    ],
    "PEC005M": [
        3,
        "下層"
    ],
    "PEC012M": [
        3,
        "下層"
    ],
    "PFA020M": [
        3,
        "下層"
    ],
    "PFA024M": [
        3,
        "下層"
    ],
    "PKB018M": [
        4,
        "最上層"
    ],
    "PKB020M": [
        4,
        "最上層"
    ],
    "PKB034M": [
        4,
        "最上層"
    ],
    "PKD004M": [
        4,
        "最上層"
    ],
    "PKF002M": [
        4,
        "最上層"
    ],
    "PKF012M": [
        4,
        "最上層"
    ],
    "PKE014M": [
        4,
        "最上層"
    ],
    "PKF004M": [
        4,
        "最上層"
    ],
    "PKF024M": [
        4,
        "最上層"
    ],
    "PLC025M": [
        4,
        "最上層"
    ],
    "PLC036M": [
        4,
        "最上層"
    ],
    "PLC039M": [
        4,
        "最上層"
    ],
    "PLC044M": [
        4,
        "最上層"
    ],
    "PLC047M": [
        4,
        "最上層"
    ],
    "PLC049M": [
        4,
        "最上層"
    ],
    "PLC051M": [
        4,
        "最上層"
    ],
    "PLC053M": [
        4,
        "最上層"
    ],
    "PDA048M": [
        4,
        "最上層"
    ],
    "PDA249M": [
        4,
        "最上層"
    ],
    "PDA283M": [
        4,
        "最上層"
    ],
    "PLC014M": [
        4,
        "最上層"
    ],
    "PLC042M": [
        4,
        "最上層"
    ],
    "PME100M": [
        4,
        "最上層"
    ],
    "PME102M": [
        4,
        "最上層"
    ],
    "PME109M": [
        4,
        "最上層"
    ],
    "PMA012M": [
        4,
        "第二層"
    ],
    "PMA016M": [
        4,
        "第二層"
    ],
    "PMA026M": [
        4,
        "第二層"
    ],
    "PMA029M": [
        4,
        "第二層"
    ],
    "PMA032M": [
        4,
        "第二層"
    ],
    "PMA050M": [
        4,
        "第二層"
    ],
    "PMC005M": [
        4,
        "第二層"
    ],
    "PMC010M": [
        4,
        "第二層"
    ],
    "PMC020M": [
        4,
        "第二層"
    ],
    "PMC021M": [
        4,
        "第二層"
    ],
    "PMC026M": [
        4,
        "第二層"
    ],
    "PMC030M": [
        4,
        "第二層"
    ],
    "PMC037M": [
        4,
        "第二層"
    ],
    "PMC038M": [
        4,
        "第二層"
    ],
    "PMC039M": [
        4,
        "第二層"
    ],
    "PMC041M": [
        4,
        "第二層"
    ],
    "PMC042M": [
        4,
        "第二層"
    ],
    "PMC043M": [
        4,
        "第二層"
    ],
    "PMC046M": [
        4,
        "第二層"
    ],
    "PMC054M": [
        4,
        "第二層"
    ],
    "PMC065M": [
        4,
        "第二層"
    ],
    "PMC068M": [
        4,
        "第二層"
    ],
    "PCM073M": [
        4,
        "第二層"
    ],
    "PMC075M": [
        4,
        "第二層"
    ],
    "PMC076M": [
        4,
        "第二層"
    ],
    "PMF034M": [
        4,
        "第二層"
    ],
    "PMF066M": [
        4,
        "第二層"
    ],
    "PMF070M": [
        4,
        "第二層"
    ],
    "PMG004M": [
        4,
        "第二層"
    ],
    "PMG008M": [
        4,
        "第二層"
    ],
    "PMG024M": [
        4,
        "第二層"
    ],
    "PMG018M": [
        4,
        "第二層"
    ],
    "PMC027M": [
        4,
        "第二層"
    ],
    "PMH001M": [
        4,
        "第二層"
    ],
    "PMH002M": [
        4,
        "第二層"
    ],
    "PPA004M": [
        4,
        "第二層"
    ],
    "PQA016M": [
        4,
        "第二層"
    ],
    "PQA034M": [
        4,
        "第三層"
    ],
    "PQA040M": [
        4,
        "第三層"
    ],
    "PQB003M": [
        4,
        "第三層"
    ],
    "PQB020M": [
        4,
        "第三層"
    ],
    "PQB030M": [
        4,
        "第三層"
    ],
    "PQB028M": [
        4,
        "第三層"
    ],
    "PQB034M": [
        4,
        "第三層"
    ],
    "PRA003M": [
        4,
        "第三層"
    ],
    "PRA010M": [
        4,
        "第三層"
    ],
    "PSA002M": [
        4,
        "第三層"
    ],
    "PSA045M": [
        4,
        "第三層"
    ],
    "PSA048M": [
        4,
        "第三層"
    ],
    "PSA052M": [
        4,
        "第三層"
    ],
    "PTA012M": [
        4,
        "第三層"
    ],
    "PWB032M": [
        4,
        "第三層"
    ],
    "PWM008M": [
        4,
        "第三層"
    ],
    "PWN009M": [
        4,
        "第三層"
    ],
    "PWP020M": [
        4,
        "第三層"
    ],
    "PZA002M": [
        4,
        "第三層"
    ],
    "PZA004M": [
        4,
        "第三層"
    ],
    "PZA007M": [
        4,
        "第三層"
    ],
    "PZA009M": [
        4,
        "第三層"
    ],
    "PZA010M": [
        4,
        "第三層"
    ],
    "PZA018M": [
        4,
        "第三層"
    ],
    "PZA026M": [
        4,
        "第三層"
    ],
    "PZA028M": [
        4,
        "第三層"
    ],
    "PZA030M": [
        4,
        "第三層"
    ],
    "PZA037M": [
        4,
        "第三層"
    ],
    "PZA044M": [
        4,
        "第三層"
    ],
    "PZA068M": [
        4,
        "第三層"
    ],
    "PZA043M": [
        4,
        "第三層"
    ],
    "PZA074M": [
        4,
        "最下層"
    ],
    "PZA076M": [
        4,
        "最下層"
    ],
    "PZA079M": [
        4,
        "最下層"
    ],
    "PZA086M": [
        4,
        "最下層"
    ],
    "PZA120M": [
        4,
        "最下層"
    ],
    "PZA121M": [
        4,
        "最下層"
    ],
    "PZA127M": [
        4,
        "最下層"
    ],
    "PZA192M": [
        4,
        "最下層"
    ],
    "PZA216M": [
        4,
        "最下層"
    ],
    "PZA236M": [
        4,
        "最下層"
    ],
    "PZA238M": [
        4,
        "最下層"
    ],
    "PZA239M": [
        4,
        "最下層"
    ],
    "PZA243M": [
        4,
        "最下層"
    ],
    "PZA252M": [
        4,
        "最下層"
    ],
    "PZA271M": [
        4,
        "最下層"
    ],
    "PZA272M": [
        4,
        "最下層"
    ],
    "PZA273M": [
        4,
        "最下層"
    ],
    "PZA278M": [
        4,
        "最下層"
    ],
    "PZA280M": [
        4,
        "最下層"
    ],
    "PZA287M": [
        4,
        "最下層"
    ],
    "PZA288M": [
        4,
        "最下層"
    ],
    "PZA289M": [
        4,
        "最下層"
    ],
    "PZA290M": [
        4,
        "最下層"
    ],
    "PZA297M": [
        4,
        "最下層"
    ],
    "PZA301M": [
        4,
        "最下層"
    ],
    "PZA303M": [
        4,
        "最下層"
    ],
    "PZA305M": [
        4,
        "最下層"
    ],
    "PZA308M": [
        4,
        "最下層"
    ],
    "PZA309M": [
        4,
        "最下層"
    ],
    "PZA315M": [
        4,
        "最下層"
    ],
    "PZA323M": [
        4,
        "最下層"
    ],
    "PZA326M": [
        4,
        "最下層"
    ],
    "PZA331M": [
        4,
        "最下層"
    ],
    "PZA332M": [
        4,
        "最下層"
    ],
    "PZA335M": [
        4,
        "最下層"
    ],
    "PFB015M": [
        5,
        "最上層"
    ],
    "PFC022M": [
        5,
        "最上層"
    ],
    "PFC075M": [
        5,
        "最上層"
    ],
    "PFC077M": [
        5,
        "最上層"
    ],
    "PFC083M": [
        5,
        "最上層"
    ],
    "PFD005M": [
        5,
        "最上層"
    ],
    "PFD020M": [
        5,
        "最上層"
    ],
    "PFD028M": [
        5,
        "最上層"
    ],
    "PFD029M": [
        5,
        "最上層"
    ],
    "PFD071M": [
        5,
        "最上層"
    ],
    "PFD060M": [
        5,
        "最上層"
    ],
    "PFE007M": [
        5,
        "最上層"
    ],
    "PFE008M": [
        5,
        "最上層"
    ],
    "PFE019M": [
        5,
        "最上層"
    ],
    "PFE046M": [
        5,
        "最上層"
    ],
    "PGA004M": [
        5,
        "最上層"
    ],
    "PGA012M": [
        5,
        "最上層"
    ],
    "PGA044M": [
        5,
        "最上層"
    ],
    "PGA056M": [
        5,
        "最上層"
    ],
    "PGA062M": [
        5,
        "最上層"
    ],
    "PGA066M": [
        5,
        "最上層"
    ],
    "PGA078M": [
        5,
        "最上層"
    ],
    "PGA093M": [
        5,
        "最上層"
    ],
    "PGA099M": [
        5,
        "最上層"
    ],
    "PGA095M": [
        5,
        "最上層"
    ],
    "PGA101M": [
        5,
        "第二層"
    ],
    "PGA102M": [
        5,
        "第二層"
    ],
    "PGA103M": [
        5,
        "第二層"
    ],
    "PGA104M": [
        5,
        "第二層"
    ],
    "PGA105M": [
        5,
        "第二層"
    ],
    "PGA106M": [
        5,
        "第二層"
    ],
    "PGB004M": [
        5,
        "第二層"
    ],
    "PGB011M": [
        5,
        "第二層"
    ],
    "PGB012M": [
        5,
        "第二層"
    ],
    "PGB052M": [
        5,
        "第二層"
    ],
    "PGB063M": [
        5,
        "第二層"
    ],
    "PGB064M": [
        5,
        "第二層"
    ],
    "PGB070M": [
        5,
        "第二層"
    ],
    "PGC028M": [
        5,
        "第二層"
    ],
    "PGC040M": [
        5,
        "第二層"
    ],
    "PGC072M": [
        5,
        "第二層"
    ],
    "PGC048M": [
        5,
        "第二層"
    ],
    "PGC056M": [
        5,
        "第二層"
    ],
    "PGC078M": [
        5,
        "第二層"
    ],
    "PGF003M": [
        5,
        "第二層"
    ],
    "PGF004M": [
        5,
        "第二層"
    ],
    "PGF012M": [
        5,
        "第二層"
    ],
    "PGF030M": [
        5,
        "第三層"
    ],
    "PGF042M": [
        5,
        "第三層"
    ],
    "PGF052M": [
        5,
        "第三層"
    ],
    "PGG001M": [
        5,
        "第三層"
    ],
    "PGF068M": [
        5,
        "第三層"
    ],
    "PGB071M": [
        5,
        "第三層"
    ],
    "PGG007M": [
        5,
        "第三層"
    ],
    "PGB072M": [
        5,
        "第三層"
    ],
    "PGG010M": [
        5,
        "第三層"
    ],
    "PGG012M": [
        5,
        "第三層"
    ],
    "PGG013M": [
        5,
        "第三層"
    ],
    "PGG014M": [
        5,
        "第三層"
    ],
    "PGG026M": [
        5,
        "第三層"
    ],
    "PGG030M": [
        5,
        "第三層"
    ],
    "PGG044M": [
        5,
        "第三層"
    ],
    "PGG051M": [
        5,
        "第三層"
    ],
    "PGG054M": [
        5,
        "第三層"
    ],
    "PGG055M": [
        5,
        "第三層"
    ],
    "PGG059M": [
        5,
        "第三層"
    ],
    "PGG060M": [
        5,
        "第三層"
    ],
    "PGG067M": [
        5,
        "第三層"
    ],
    "PGG070M": [
        5,
        "第三層"
    ],
    "PGG071M": [
        5,
        "第三層"
    ],
    "PGG072M": [
        5,
        "第三層"
    ],
    "PGG088": [
        5,
        "第三層"
    ],
    "PGG089": [
        5,
        "第三層"
    ],
    "PGG091M": [
        5,
        "最下層"
    ],
    "PGG103M": [
        5,
        "最下層"
    ],
    "PGG107M": [
        5,
        "最下層"
    ],
    "PGG108M": [
        5,
        "最下層"
    ],
    "PGG112M": [
        5,
        "最下層"
    ],
    "PGG114M": [
        5,
        "最下層"
    ],
    "PGG109M": [
        5,
        "最下層"
    ],
    "PGH025M": [
        5,
        "最下層"
    ],
    "PGH040M": [
        5,
        "最下層"
    ],
    "PGH045M": [
        5,
        "最下層"
    ],
    "PGH046M": [
        5,
        "最下層"
    ],
    "PGH047M": [
        5,
        "最下層"
    ],
    "PIC001M": [
        5,
        "最下層"
    ],
    "PIC004M": [
        5,
        "最下層"
    ],
    "PIC006M": [
        5,
        "最下層"
    ],
    "PIC016M": [
        5,
        "最下層"
    ],
    "PIC008M": [
        5,
        "最下層"
    ],
    "PIC038M": [
        5,
        "最下層"
    ],
    "PIC045M": [
        5,
        "最下層"
    ],
    "PIG043M": [
        5,
        "最下層"
    ],
    "PIG088M": [
        5,
        "最下層"
    ],
    "PIG093M": [
        5,
        "最下層"
    ],
    "PIG101M": [
        5,
        "最下層"
    ],
    "PIG103M": [
        5,
        "最下層"
    ],
    "PIH002M": [
        5,
        "最下層"
    ],
    "PIH014M": [
        5,
        "最下層"
    ],
    "PKA050M": [
        5,
        "最下層"
    ],
    "PKA068M": [
        5,
        "最下層"
    ],
    "PKA091M": [
        5,
        "最下層"
    ],
    "PKB002M": [
        5,
        "最下層"
    ],
    "PKB004M": [
        5,
        "最下層"
    ],
    "PME117M": [
        6,
        "上層"
    ],
    "PME122M": [
        6,
        "上層"
    ],
    "PZA080M": [
        6,
        "下層"
    ],
    "PMF068M": [
        6,
        "下層"
    ],
    "PZA232M": [
        6,
        "下層"
    ],
    "PDA044M": [
        7,
        "最上層"
    ],
    "PDA045M": [
        7,
        "最上層"
    ],
    "PDA050M": [
        7,
        "最上層"
    ],
    "PDA063M": [
        7,
        "最上層"
    ],
    "PDA073M": [
        7,
        "最上層"
    ],
    "PDA024M": [
        7,
        "最上層"
    ],
    "PDA039M": [
        7,
        "最上層"
    ],
    "PDA042M": [
        7,
        "最上層"
    ],
    "PDA086M": [
        7,
        "最上層"
    ],
    "PDA088M": [
        7,
        "最上層"
    ],
    "PDA090M": [
        7,
        "最上層"
    ],
    "PDA091M": [
        7,
        "最上層"
    ],
    "PDA098M": [
        7,
        "最上層"
    ],
    "PDA184M": [
        7,
        "最上層"
    ],
    "PDA200M": [
        7,
        "最上層"
    ],
    "PDA219M": [
        7,
        "最上層"
    ],
    "PDA220M": [
        7,
        "最上層"
    ],
    "PDA221M": [
        7,
        "最上層"
    ],
    "PDA222M": [
        7,
        "最上層"
    ],
    "PDA225M": [
        7,
        "最上層"
    ],
    "PDA228M": [
        7,
        "最上層"
    ],
    "PDA232M": [
        7,
        "最上層"
    ],
    "PDA235M": [
        7,
        "最上層"
    ],
    "PDA236M": [
        7,
        "最上層"
    ],
    "PDA240M": [
        7,
        "最上層"
    ],
    "PDA242M": [
        7,
        "最上層"
    ],
    "PDA245M": [
        7,
        "最上層"
    ],
    "PDA258M": [
        7,
        "最上層"
    ],
    "PDA269M": [
        7,
        "最上層"
    ],
    "PDA270M": [
        7,
        "最上層"
    ],
    "PDA279M": [
        7,
        "最上層"
    ],
    "PDA299M": [
        7,
        "第二層"
    ],
    "PDA300M": [
        7,
        "第二層"
    ],
    "PDA302M": [
        7,
        "第二層"
    ],
    "PDA304M": [
        7,
        "第二層"
    ],
    "PDA306M": [
        7,
        "第二層"
    ],
    "PDA307M": [
        7,
        "第二層"
    ],
    "PDA313M": [
        7,
        "第二層"
    ],
    "PDA280M": [
        7,
        "第二層"
    ],
    "PDA282M": [
        7,
        "第二層"
    ],
    "PDA295M": [
        7,
        "第二層"
    ],
    "PDA297M": [
        7,
        "第二層"
    ],
    "PDA298M": [
        7,
        "第二層"
    ],
    "PDA314M": [
        7,
        "第二層"
    ],
    "PDA321M": [
        7,
        "第二層"
    ],
    "PDA326M": [
        7,
        "第二層"
    ],
    "PDA328M": [
        7,
        "第二層"
    ],
    "PDA329M": [
        7,
        "第二層"
    ],
    "PDA330M": [
        7,
        "第二層"
    ],
    "PDA331M": [
        7,
        "第二層"
    ],
    "PDA332M": [
        7,
        "第二層"
    ],
    "PDA333M": [
        7,
        "第二層"
    ],
    "PDA334M": [
        7,
        "第二層"
    ],
    "PDA335M": [
        7,
        "第二層"
    ],
    "PDA338M": [
        7,
        "第二層"
    ],
    "PDA339M": [
        7,
        "第二層"
    ],
    "PDA344M": [
        7,
        "第二層"
    ],
    "PDA346M": [
        7,
        "第二層"
    ],
    "PDA347M": [
        7,
        "第二層"
    ],
    "PDA349M": [
        7,
        "第二層"
    ],
    "PDA353M": [
        7,
        "第二層"
    ],
    "PDA354M": [
        7,
        "第二層"
    ],
    "PDA360M": [
        7,
        "第二層"
    ],
    "PDA361M": [
        7,
        "第二層"
    ],
    "PDA362M": [
        7,
        "第二層"
    ],
    "PDA363M": [
        7,
        "第二層"
    ],
    "PDA364M": [
        7,
        "第二層"
    ],
    "PEB006M": [
        7,
        "第三層"
    ],
    "PEC008M": [
        7,
        "第三層"
    ],
    "PEC014M": [
        7,
        "第三層"
    ],
    "PEC026M": [
        7,
        "第三層"
    ],
    "PDA365M": [
        7,
        "第三層"
    ],
    "PDA366M": [
        7,
        "第三層"
    ],
    "PDA367M": [
        7,
        "第三層"
    ],
    "PDA368M": [
        7,
        "第三層"
    ],
    "PDA369M": [
        7,
        "第三層"
    ],
    "PDA377M": [
        7,
        "第三層"
    ],
    "PDA378M": [
        7,
        "第三層"
    ],
    "PEA002M": [
        7,
        "第三層"
    ],
    "PEC028M": [
        7,
        "第三層"
    ],
    "PEC030M": [
        7,
        "第三層"
    ],
    "PEC032M": [
        7,
        "第三層"
    ],
    "PEC034M": [
        7,
        "第三層"
    ],
    "PEC039M": [
        7,
        "第三層"
    ],
    "PED020M": [
        7,
        "第三層"
    ],
    "PED028M": [
        7,
        "第三層"
    ],
    "PED048M": [
        7,
        "第三層"
    ],
    "PED050M": [
        7,
        "第三層"
    ],
    "PED052M": [
        7,
        "第三層"
    ],
    "PED056M": [
        7,
        "第三層"
    ],
    "PED066M": [
        7,
        "第三層"
    ],
    "PED068M": [
        7,
        "第三層"
    ],
    "PFA005M": [
        7,
        "第三層"
    ],
    "PFA006M": [
        7,
        "第三層"
    ],
    "PFA012M": [
        7,
        "第三層"
    ],
    "PFA009M": [
        7,
        "第三層"
    ],
    "PFA048M": [
        7,
        "最下層"
    ],
    "PFA060M": [
        7,
        "最下層"
    ],
    "PFA084M": [
        7,
        "最下層"
    ],
    "PFA026M": [
        7,
        "最下層"
    ],
    "PFA027M": [
        7,
        "最下層"
    ],
    "PFA036M": [
        7,
        "最下層"
    ],
    "PFA039M": [
        7,
        "最下層"
    ],
    "PFA041M": [
        7,
        "最下層"
    ],
    "PFA086M": [
        7,
        "最下層"
    ],
    "PFA92M": [
        7,
        "最下層"
    ],
    "PFA095M": [
        7,
        "最下層"
    ],
    "PFA102M": [
        7,
        "最下層"
    ],
    "PFA110M": [
        7,
        "最下層"
    ],
    "PFA116M": [
        7,
        "最下層"
    ],
    "PFA120M": [
        7,
        "最下層"
    ],
    "PFA121M": [
        7,
        "最下層"
    ],
    "PFA148M": [
        7,
        "最下層"
    ],
    "PAA001M": [
        8,
        "最上層"
    ],
    "PAA005M": [
        8,
        "最上層"
    ],
    "PAA012M": [
        8,
        "最上層"
    ],
    "PAA014M": [
        8,
        "最上層"
    ],
    "PAA032M": [
        8,
        "最上層"
    ],
    "PAA045M": [
        8,
        "最上層"
    ],
    "PAA050M": [
        8,
        "最上層"
    ],
    "PBA005M": [
        8,
        "最上層"
    ],
    "PBA009M": [
        8,
        "最上層"
    ],
    "PBA016M": [
        8,
        "最上層"
    ],
    "PBA020M": [
        8,
        "最上層"
    ],
    "PBA044M": [
        8,
        "最上層"
    ],
    "PCA006M": [
        8,
        "最上層"
    ],
    "PCC008M": [
        8,
        "最上層"
    ],
    "PCB026M": [
        8,
        "最上層"
    ],
    "PCC004M": [
        8,
        "最上層"
    ],
    "PCC010M": [
        8,
        "最上層"
    ],
    "PCC016M": [
        8,
        "最上層"
    ],
    "PCC040M": [
        8,
        "最上層"
    ],
    "PCC076M": [
        8,
        "最上層"
    ],
    "PME123M": [
        8,
        "第二層"
    ],
    "PME127M": [
        8,
        "第二層"
    ],
    "PME128M": [
        8,
        "第二層"
    ],
    "PME130M": [
        8,
        "第二層"
    ],
    "PMF074M": [
        8,
        "第二層"
    ],
    "PCC104M": [
        8,
        "第二層"
    ],
    "PCC136M": [
        8,
        "第二層"
    ],
    "PCC148M": [
        8,
        "第二層"
    ],
    "PCC150M": [
        8,
        "第二層"
    ],
    "PCC162M": [
        8,
        "第二層"
    ],
    "PCC173M": [
        8,
        "第二層"
    ],
    "PCC180M": [
        8,
        "第二層"
    ],
    "PCC184M": [
        8,
        "第二層"
    ],
    "PCC309M": [
        8,
        "第二層"
    ],
    "PCC336M": [
        8,
        "第二層"
    ],
    "PCC345M": [
        8,
        "第二層"
    ],
    "PCC352M": [
        8,
        "第二層"
    ],
    "PCC356M": [
        8,
        "第二層"
    ],
    "PCD008M": [
        8,
        "第二層"
    ],
    "PCD012M": [
        8,
        "第二層"
    ],
    "PCD020M": [
        8,
        "第二層"
    ],
    "PCD024M": [
        8,
        "第二層"
    ],
    "PCD026M": [
        8,
        "第二層"
    ],
    "PCD028M": [
        8,
        "第二層"
    ],
    "PCD037M": [
        8,
        "第二層"
    ],
    "PCD038M": [
        8,
        "第三層"
    ],
    "PCD039M": [
        8,
        "第三層"
    ],
    "PCD040M": [
        8,
        "第三層"
    ],
    "PCD042M": [
        8,
        "第三層"
    ],
    "PCE002M": [
        8,
        "第三層"
    ],
    "PCE004M": [
        8,
        "第三層"
    ],
    "PCE010M": [
        8,
        "第三層"
    ],
    "PCE012M": [
        8,
        "第三層"
    ],
    "PCE014M": [
        8,
        "第三層"
    ],
    "PCE018M": [
        8,
        "第三層"
    ],
    "PCE024M": [
        8,
        "第三層"
    ],
    "PCE036M": [
        8,
        "第三層"
    ],
    "PCE037M": [
        8,
        "第三層"
    ],
    "PCF008M": [
        8,
        "第三層"
    ],
    "PCF037M": [
        8,
        "第三層"
    ],
    "PCG004M": [
        8,
        "第三層"
    ],
    "PCG020M": [
        8,
        "第三層"
    ],
    "PZA234M": [
        8,
        "最下層"
    ],
    "PZA255M": [
        8,
        "最下層"
    ],
    "PCG038M": [
        8,
        "最下層"
    ],
    "PCG040M": [
        8,
        "最下層"
    ],
    "PCH003M": [
        8,
        "最下層"
    ],
    "PCH006M": [
        8,
        "最下層"
    ],
    "PCH018M": [
        8,
        "最下層"
    ],
    "PCH044M": [
        8,
        "最下層"
    ],
    "PCH066M": [
        8,
        "最下層"
    ],
    "PCH098M": [
        8,
        "最下層"
    ],
    "PCH106M": [
        8,
        "最下層"
    ],
    "PCH108M": [
        8,
        "最下層"
    ],
    "PCH119M": [
        8,
        "最下層"
    ],
    "PCH121M": [
        8,
        "最下層"
    ],
    "PCH129M": [
        8,
        "最下層"
    ],
    "PCH130M": [
        8,
        "最下層"
    ],
    "PCH131M": [
        8,
        "最下層"
    ],
    "PCH133M": [
        8,
        "最下層"
    ],
    "PBA010M": [
        9,
        "上層"
    ],
    "PBA002M": [
        9,
        "上層"
    ],
    "PCH076M": [
        9,
        "下層"
    ],
    "PME016M": [
        9,
        "上層"
    ],
    "PME006M": [
        9,
        "上層"
    ],
    "PLC033M": [
        9,
        "上層"
    ],
    "PME026M": [
        9,
        "上層"
    ],
    "PME024M": [
        9,
        "上層"
    ],
    "PME116M": [
        9,
        "上層"
    ],
    "PME096M": [
        9,
        "上層"
    ],
    "PME072M": [
        9,
        "上層"
    ],
    "PME076M": [
        9,
        "上層"
    ],
    "PDA324M": [
        9,
        "下層"
    ],
    "PDA065M": [
        9,
        "下層"
    ],
    "PRA008M": [
        9,
        "下層"
    ],
    "PMG026M": [
        9,
        "下層"
    ],
    "PLD042M": [
        9,
        "下層"
    ],
    "PSA096M": [
        9,
        "下層"
    ],
    "PSA060M": [
        9,
        "下層"
    ],
    "PSA051M": [
        9,
        "下層"
    ],
    "PZA071M": [
        9,
        "下層"
    ],
    "PZA024M": [
        9,
        "下層"
    ],
    "PZA017M": [
        9,
        "下層"
    ],
    "PSA092M": [
        9,
        "下層"
    ],
    "PME139M": [
        10,
        "上層"
    ],
    "PME138M": [
        10,
        "上層"
    ],
    "PME137M": [
        10,
        "上層"
    ],
    "PZA266M": [
        10,
        "下層"
    ],
    "PZA285M": [
        10,
        "下層"
    ],
    "PZA279M": [
        10,
        "下層"
    ],
    "PIG006M": [
        11,
        "上層"
    ],
    "PID012M": [
        11,
        "上層"
    ],
    "PIC032M": [
        11,
        "上層"
    ],
    "PIG091M": [
        11,
        "上層"
    ],
    "PIE008M": [
        11,
        "上層"
    ],
    "PIB013M": [
        11,
        "下層"
    ],
    "PKD056M": [
        11,
        "下層"
    ],
    "PKD055M": [
        11,
        "下層"
    ],
    "PKF014M": [
        11,
        "下層"
    ],
    "PKE012M": [
        11,
        "下層"
    ],
    "PRA055M": [
        11,
        "下層"
    ],
    "PIH006M": [
        12,
        "上層"
    ],
    "PIH012M": [
        12,
        "上層"
    ],
    "PKA003M": [
        12,
        "上層"
    ],
    "PKE019M": [
        12,
        "上層"
    ],
    "PKA029M": [
        12,
        "上層"
    ],
    "PKA040M": [
        12,
        "上層"
    ],
    "PKA048M": [
        12,
        "上層"
    ],
    "PKA096M": [
        12,
        "上層"
    ],
    "PKB021M": [
        12,
        "上層"
    ],
    "PQA018M": [
        12,
        "上層"
    ],
    "PKB030M": [
        12,
        "上層"
    ],
    "PKF016M": [
        12,
        "下層"
    ],
    "PKF045M": [
        12,
        "下層"
    ],
    "PKF048M": [
        12,
        "下層"
    ],
    "PLB001M": [
        12,
        "下層"
    ],
    "PLB002M": [
        12,
        "下層"
    ],
    "PLC034M": [
        12,
        "下層"
    ],
    "PLC035M": [
        12,
        "下層"
    ],
    "PLC037M": [
        12,
        "下層"
    ],
    "PLC041M": [
        12,
        "下層"
    ],
    "PLC045M": [
        12,
        "下層"
    ],
    "PLC048M": [
        12,
        "下層"
    ],
    "PDA020M": [
        "t",
        "原西藥庫冷藏櫃右邊第一區"
    ],
    "PDA176M": [
        "t",
        "原西藥庫冷藏櫃右邊第一區"
    ],
    "PDA178M": [
        "t",
        "原西藥庫冷藏櫃右邊第一區"
    ],
    "PDA275M": [
        "t",
        "原西藥庫冷藏櫃右邊第一區"
    ],
    "PDA374M": [
        "t",
        "原西藥庫冷藏櫃右邊第一區"
    ],
    "PDA375M": [
        "t",
        "原西藥庫冷藏櫃右邊第一區"
    ],
    "PMA021M": [
        "t",
        "原西藥庫冷藏櫃右邊第一區"
    ],
    "PZA210M": [
        "t",
        "原西藥庫冷藏櫃右邊第一區"
    ],
    "P6B008M": [
        "t",
        "原西藥庫冷藏櫃右邊第一區"
    ],
    "PDA040M": [
        "t",
        "原西藥庫冷藏櫃右邊第一區，但目前無庫存"
    ],
    "PFA146M": [
        7,
        "最下層"
    ],
    "PFA147M": [
        7,
        "最下層"
    ]
}